binotree/__init__.py
binotree/tree.py
binotree/images/.DS_Store
binotree/images/BSexplanationN.png
binotree/images/BSpricing.png
binotree/images/BSput.png
binotree/images/d1.png
binotree/images/d2.png
binotree/images/dFormula.png
binotree/images/deltaPlotDemo.png
binotree/images/deltaPlotPeriodsDemo.png
binotree/images/dfTreeDemo.png
binotree/images/excelDemo.png
binotree/images/excelPortDemo.png
binotree/images/nonrecExcelDemo.png
binotree/images/periodsPlotDemo.png
binotree/images/pricePlotDemo.png
binotree/images/pricePlotStrikeDemo.png
binotree/images/qFormula.png
binotree/images/qFormulaNoncont.png
binotree/images/replicatingBond.png
binotree/images/replicatingBondNoncont.png
binotree/images/replicatingDelta.png
binotree/images/replicatingDeltaNoncont.png
binotree/images/replicatingExplanation.png
binotree/images/replicatingPricing.png
binotree/images/riskNeutralPricing.png
binotree/images/spotsPlot30Demo.png
binotree/images/spotsPlotDemo.png
binotree/images/treeCall.png
binotree/images/uFormula.png
binotree-1.0.5.dist-info/LICENSE.txt
binotree-1.0.5.dist-info/METADATA
binotree-1.0.5.dist-info/WHEEL
binotree-1.0.5.dist-info/top_level.txt
binotree-1.0.5.dist-info/RECORD
