Metadata-Version: 2.1
Name: binotree
Version: 1.0.5
Summary: class for creating binomial trees for options pricing
Home-page: https://github.com/EHamre/optionsBinoTree
Author: Espen Hamre
Author-email: devespen@outlook.com
License: MIT
Platform: UNKNOWN
Classifier: Programming Language :: Python :: 3
Classifier: License :: OSI Approved :: MIT License
Classifier: Operating System :: OS Independent
Requires-Python: >=3.7
License-File: LICENSE.txt
Requires-Dist: scipy
Requires-Dist: seaborn
Requires-Dist: matplotlib
Requires-Dist: pandas
Requires-Dist: XlsxWriter
Requires-Dist: numpy
